gene_fetch/__init__.py
gene_fetch/core.py
gene_fetch/entrez_handler.py
gene_fetch/main.py
gene_fetch/output_manager.py
gene_fetch/processors.py
gene_fetch/sequence_processor.py
gene_fetch-1.0.21.dist-info/LICENSE
gene_fetch-1.0.21.dist-info/METADATA
gene_fetch-1.0.21.dist-info/WHEEL
gene_fetch-1.0.21.dist-info/entry_points.txt
gene_fetch-1.0.21.dist-info/RECORD
