Metadata-Version: 2.3
Name: gene-fetch
Version: 1.0.21
Summary: Gene Fetch: High-throughput NCBI Sequence Retrieval Tool
License: MIT
Keywords: bioinformatics,ncbi,sequence,genomics,taxonomy,barcodes
Author: D. Parsons
Author-email: d.parsons@nhm.ac.uk>, B. Price <b.price@nhm.ac.uk
Requires-Python: >=3.9
Classifier: Development Status :: 5 - Production/Stable
Classifier: Intended Audience :: Science/Research
Classifier: License :: OSI Approved :: MIT License
Classifier: Programming Language :: Python :: 3
Classifier: Programming Language :: Python :: 3.9
Classifier: Programming Language :: Python :: 3.10
Classifier: Programming Language :: Python :: 3.11
Classifier: Programming Language :: Python :: 3.12
Classifier: Programming Language :: Python :: 3.13
Classifier: Topic :: Scientific/Engineering :: Bio-Informatics
Requires-Dist: biopython (>=1.80)
Requires-Dist: ratelimit (>=2.2.1)
Project-URL: Bug Tracker, https://github.com/bge-barcoding/gene_fetch/issues
Project-URL: Homepage, https://github.com/bge-barcoding/gene_fetch
Project-URL: Repository, https://github.com/bge-barcoding/gene_fetch
